ctao_wms_clients-0.5.2.dist-info/licenses/LICENSE
wms/__init__.py
wms/_version.py
wms/tests/__init__.py
wms/tests/conftest.py
wms/tests/test_dirac_basic.py
wms/tests/test_utils.py
wms/tests/utils.py
wms/tests/cwl/basic_workflow/data-generation.cwl
wms/tests/cwl/basic_workflow/gaussian-fit-workflow.cwl
wms/tests/cwl/basic_workflow/gaussian-fit.cwl
wms/tests/cwl/basic_workflow/gaussian_fit.py
wms/tests/cwl/basic_workflow/inputs-gaussian-fit-complete.yaml
wms/tests/cwl/basic_workflow/random_data_gen.py
wms/tests/cwl/hello_world/container_example.cwl
wms/tests/cwl/hello_world/container_example_inputs.yaml
wms/tests/cwl/hello_world/hello_world.cwl
wms/tests/cwl/hello_world/hello_world.py
wms/tests/cwl/hello_world/input.yml
wms/tests/cwl/scatter_workflow/generate_names.cwl
wms/tests/cwl/scatter_workflow/input_scatter_workflow.yaml
wms/tests/cwl/scatter_workflow/scatter_workflow.cwl
wms/tests/cwl/scatter_workflow/script_1.py
wms/tests/cwl/scatter_workflow/script_2.py
wms/tests/cwl/scatter_workflow/step_1.cwl
wms/tests/cwl/scatter_workflow/step_2.cwl
ctao_wms_clients-0.5.2.dist-info/METADATA
ctao_wms_clients-0.5.2.dist-info/WHEEL
ctao_wms_clients-0.5.2.dist-info/top_level.txt
ctao_wms_clients-0.5.2.dist-info/RECORD
